src/__init__.py
src/cli.py
src/core/__init__.py
src/core/backends.py
src/core/controller.py
src/core/metadata.py
src/core/remote.py
src/core/storage.py
src/integrations/__init__.py
src/integrations/airflow.py
src/integrations/prefect.py
src/web/app.py
src/web/templates/commit.html
src/web/templates/diff.html
src/web/templates/index.html
src/web/templates/layout.html
data_time_machine-0.2.3.dist-info/METADATA
data_time_machine-0.2.3.dist-info/WHEEL
data_time_machine-0.2.3.dist-info/entry_points.txt
data_time_machine-0.2.3.dist-info/RECORD
