Metadata-Version: 2.4
Name: data-time-machine
Version: 0.2.3
Summary: A git-like state management system for data pipelines
Project-URL: Homepage, https://github.com/azmatsiddique/data-time-machine
Project-URL: Repository, https://github.com/azmatsiddique/data-time-machine
Project-URL: Issues, https://github.com/azmatsiddique/data-time-machine/issues
Author-email: Azmat Siddique <azmat.siddique.98@gmail.com>
Requires-Python: >=3.10
Requires-Dist: click>=8.1.7
Requires-Dist: pydantic>=2.5.3
Provides-Extra: all
Requires-Dist: azure-storage-blob>=12.17.0; extra == 'all'
Requires-Dist: boto3>=1.28.0; extra == 'all'
Requires-Dist: fastapi>=0.100.0; extra == 'all'
Requires-Dist: google-cloud-storage>=2.10.0; extra == 'all'
Requires-Dist: jinja2>=3.1.0; extra == 'all'
Requires-Dist: uvicorn>=0.23.0; extra == 'all'
Provides-Extra: cloud
Requires-Dist: azure-storage-blob>=12.17.0; extra == 'cloud'
Requires-Dist: boto3>=1.28.0; extra == 'cloud'
Requires-Dist: google-cloud-storage>=2.10.0; extra == 'cloud'
Provides-Extra: test
Requires-Dist: pytest>=7.4.0; extra == 'test'
Provides-Extra: web
Requires-Dist: fastapi>=0.100.0; extra == 'web'
Requires-Dist: jinja2>=3.1.0; extra == 'web'
Requires-Dist: uvicorn>=0.23.0; extra == 'web'
